reviews_lm_scorer/__init__.py
reviews_lm_scorer/ai_review_generator/__init__.py
reviews_lm_scorer/ai_review_generator/base.py
reviews_lm_scorer/ai_review_generator/openai_generator.py
reviews_lm_scorer/hf_manager.py
reviews_lm_scorer/lm_scorer/__init__.py
reviews_lm_scorer/lm_scorer/base.py
reviews_lm_scorer/lm_scorer/bert_lm_scorer.py
reviews_lm_scorer/prompt_builder/__init__.py
reviews_lm_scorer/prompt_builder/textblob_sentiment_analyser.py
reviews_lm_scorer/prompt_template.py
reviews_lm_scorer/prompt_templates.json
reviews_lm_scorer/utils/__init__.py
reviews_lm_scorer/utils/config.py
reviews_lm_scorer/utils/framework_check.py
reviews_lm_scorer-0.2.0.dist-info/METADATA
reviews_lm_scorer-0.2.0.dist-info/WHEEL
reviews_lm_scorer-0.2.0.dist-info/RECORD
